gcustat/__init__.py
gcustat/__main__.py
gcustat/cli.py
gcustat/core.py
gcustat/gcu_smi.py
gcustat-0.0.7.dist-info/LICENSE
gcustat-0.0.7.dist-info/METADATA
gcustat-0.0.7.dist-info/WHEEL
gcustat-0.0.7.dist-info/entry_points.txt
gcustat-0.0.7.dist-info/top_level.txt
gcustat-0.0.7.dist-info/RECORD
