Metadata-Version: 2.1
Name: gcustat
Version: 0.0.7
Summary: An utility to monitor Enflame GCU card status and usage
Home-page: https://www.enflame-tech.com/
Author: xinmin.peng
Author-email: xinmin.peng@enflame-tech.com
License: MIT
Keywords: enflame gcu monitoring gcustat
Platform: UNKNOWN
Classifier: License :: OSI Approved :: MIT License
Classifier: Operating System :: POSIX :: Linux
Classifier: Programming Language :: Python :: 3
Classifier: Topic :: System :: Monitoring
Requires-Python: >=3.6
Requires-Dist: blessed (>=1.17.1)
Requires-Dist: six (>=1.7)
